<xml xmlns="https://developers.google.com/blockly/xml">
  <variables>
    <variable id="*gmAd_(=!Xy(r-Tx@gL2">leds</variable>
    <variable id="k~65$xi@)yA=N(!g@6i?">i</variable>
    <variable id="`AoG#YNXouT5iDHZm~e`">button</variable>
    <variable id="DdNRh2WOEyCY}N6BX4{3">idx</variable>
  </variables>
  <block type="variables_set" id="zc5gUbX_tFe)q[8~S/L:" x="-938" y="-112">
    <field name="VAR" id="*gmAd_(=!Xy(r-Tx@gL2">leds</field>
    <value name="VALUE">
      <block type="lists_create_with" id="xZ0|H/_?,Cjn0[Jw@F:;">
        <mutation items="3"/>
        <value name="ADD0">
          <block type="gpio_create_pinobj" id="Io$yy?GqC00}hj-[9@GS">
            <field name="type">OUT</field>
            <value name="pin">
              <shadow type="pinout" id="J.jCd7F3f4O-pHFmKPqn">
                <field name="PIN">15</field>
              </shadow>
            </value>
          </block>
        </value>
        <value name="ADD1">
          <block type="gpio_create_pinobj" id="ze9%YU26[}u*l.O|nBDc">
            <field name="type">OUT</field>
            <value name="pin">
              <shadow type="pinout" id="XPjO=`Z=(~Ce9cY/L3h#">
                <field name="PIN">12</field>
              </shadow>
            </value>
          </block>
        </value>
        <value name="ADD2">
          <block type="gpio_create_pinobj" id="o1A7fTmv1l:QXO9}MIc@">
            <field name="type">OUT</field>
            <value name="pin">
              <shadow type="pinout" id="Gov9ANwiw^Wv-EMD|0eu">
                <field name="PIN">13</field>
              </shadow>
            </value>
          </block>
        </value>
      </block>
    </value>
    <next>
      <block type="variables_set" id="!sUo=gqI26GdK~gLbVc7">
        <field name="VAR" id="`AoG#YNXouT5iDHZm~e`">button</field>
        <value name="VALUE">
          <block type="gpio_create_pinobj" id=";sr2T0nJCs`~)bIaOoyY">
            <field name="type">IN</field>
            <value name="pin">
              <shadow type="pinout" id="a7N:t]w{um}@n_#JIlK@">
                <field name="PIN">4</field>
              </shadow>
            </value>
          </block>
        </value>
        <next>
          <block type="procedures_callnoreturn" id="ykK^-w#5k/CEjx6~dH[m">
            <mutation name="leds_off"/>
            <next>
              <block type="variables_set" id="hcMc5jaah4ai+ou$M9e(">
                <field name="VAR" id="DdNRh2WOEyCY}N6BX4{3">idx</field>
                <value name="VALUE">
                  <block type="math_number" id="qO-vE,EdSPcQ;yK$SxU?">
                    <field name="NUM">1</field>
                  </block>
                </value>
                <next>
                  <block type="controls_whileUntil" id="3yPBx~MX#zk!BEKRw/GL">
                    <field name="MODE">WHILE</field>
                    <value name="BOOL">
                      <block type="logic_boolean" id="C#,gWU)nX8_F{Oe5?^OO">
                        <field name="BOOL">TRUE</field>
                      </block>
                    </value>
                    <statement name="DO">
                      <block type="controls_if" id="Mum3~aM2r6+mwcLBdOD)">
                        <value name="IF0">
                          <block type="logic_negate" id="+tuRzF{3F0{Md_3#n^FQ">
                            <value name="BOOL">
                              <block type="gpio_get_pinobj" id="P3V+~v_Ba!bS~X+1n;IX">
                                <value name="obj">
                                  <block type="variables_get" id="03^6Z5pn1-o;t0N:b|W8">
                                    <field name="VAR" id="`AoG#YNXouT5iDHZm~e`">button</field>
                                  </block>
                                </value>
                              </block>
                            </value>
                          </block>
                        </value>
                        <statement name="DO0">
                          <block type="procedures_callnoreturn" id="F3TL?M3bQW0U47!//I.w">
                            <mutation name="leds_off"/>
                            <next>
                              <block type="gpio_set_pinobj" id="Gcj4Pb:cla{!`g!v.(kG">
                                <value name="obj">
                                  <block type="lists_getIndex" id="V}^^v9tu+Y~28@6=pL}!">
                                    <mutation statement="false" at="true"/>
                                    <field name="MODE">GET</field>
                                    <field name="WHERE">FROM_START</field>
                                    <value name="VALUE">
                                      <block type="variables_get" id=".qv,/3HfY4bsc[U3Yw-E">
                                        <field name="VAR" id="*gmAd_(=!Xy(r-Tx@gL2">leds</field>
                                      </block>
                                    </value>
                                    <value name="AT">
                                      <block type="variables_get" id="aru{G32(qe5l;,N23IUQ">
                                        <field name="VAR" id="DdNRh2WOEyCY}N6BX4{3">idx</field>
                                      </block>
                                    </value>
                                  </block>
                                </value>
                                <value name="value">
                                  <shadow type="logic_boolean" id="M83w/XeQ-0.b(El2KI;U">
                                    <field name="BOOL">TRUE</field>
                                  </shadow>
                                </value>
                                <next>
                                  <block type="variables_set" id="WAy`*8zXO[!46tE@b$;P">
                                    <field name="VAR" id="DdNRh2WOEyCY}N6BX4{3">idx</field>
                                    <value name="VALUE">
                                      <block type="math_arithmetic" id="7X*7Es7qW?ivw]75o(K7">
                                        <field name="OP">ADD</field>
                                        <value name="A">
                                          <shadow type="math_number" id="3-af0sGw-0aXE0DFGiL3">
                                            <field name="NUM">1</field>
                                          </shadow>
                                          <block type="variables_get" id="5Zz3.PAWc[X/nVK1^#bY">
                                            <field name="VAR" id="DdNRh2WOEyCY}N6BX4{3">idx</field>
                                          </block>
                                        </value>
                                        <value name="B">
                                          <shadow type="math_number" id="$ddDGN=R%nJ%(b(Vk|xv">
                                            <field name="NUM">1</field>
                                          </shadow>
                                        </value>
                                      </block>
                                    </value>
                                    <next>
                                      <block type="controls_if" id="lea%EH/-v9t4!v@L8iz[">
                                        <value name="IF0">
                                          <block type="logic_compare" id="smd}R:@[/,qy_ZxSl3|`">
                                            <field name="OP">GT</field>
                                            <value name="A">
                                              <block type="variables_get" id="u5hW6PY^$aZUa]:/)%=J">
                                                <field name="VAR" id="DdNRh2WOEyCY}N6BX4{3">idx</field>
                                              </block>
                                            </value>
                                            <value name="B">
                                              <block type="math_number" id="jfyrxY/D+v+H5.s#pmmP">
                                                <field name="NUM">3</field>
                                              </block>
                                            </value>
                                          </block>
                                        </value>
                                        <statement name="DO0">
                                          <block type="variables_set" id="T.Dy[atQ:6rED2d32Hzy">
                                            <field name="VAR" id="DdNRh2WOEyCY}N6BX4{3">idx</field>
                                            <value name="VALUE">
                                              <block type="math_number" id="Ytw1;$b?/h1|SI~B+`f}">
                                                <field name="NUM">1</field>
                                              </block>
                                            </value>
                                          </block>
                                        </statement>
                                        <next>
                                          <block type="controls_whileUntil" id="6qmcIC=AjNLQds0I(6-?">
                                            <field name="MODE">WHILE</field>
                                            <value name="BOOL">
                                              <block type="logic_negate" id="wE%Sv|{y?sz!QtViXqwu">
                                                <value name="BOOL">
                                                  <block type="gpio_get_pinobj" id="+1tHi8/{p*[{T|N!FkkH">
                                                    <value name="obj">
                                                      <block type="variables_get" id="/g=0fiGqK.-Hb+Np[eHp">
                                                        <field name="VAR" id="`AoG#YNXouT5iDHZm~e`">button</field>
                                                      </block>
                                                    </value>
                                                  </block>
                                                </value>
                                              </block>
                                            </value>
                                          </block>
                                        </next>
                                      </block>
                                    </next>
                                  </block>
                                </next>
                              </block>
                            </next>
                          </block>
                        </statement>
                      </block>
                    </statement>
                  </block>
                </next>
              </block>
            </next>
          </block>
        </next>
      </block>
    </next>
  </block>
  <block type="procedures_defnoreturn" id="mt:^Es*tjwbJJt4=q`~," x="237" y="38">
    <field name="NAME">leds_off</field>
    <comment pinned="false" h="80" w="160">Describe this function...</comment>
    <statement name="STACK">
      <block type="controls_forEach" id="%27(=_Bf/0kn*E1CZ{DI">
        <field name="VAR" id="k~65$xi@)yA=N(!g@6i?">i</field>
        <value name="LIST">
          <block type="variables_get" id="vUC4:y.6O8J_7(u;OBe.">
            <field name="VAR" id="*gmAd_(=!Xy(r-Tx@gL2">leds</field>
          </block>
        </value>
        <statement name="DO">
          <block type="gpio_set_pinobj" id="1n.W)#n;~#v8)5!Sx^V`">
            <value name="obj">
              <block type="variables_get" id="cl/v*p.LoS)~GT`YV5:y">
                <field name="VAR" id="k~65$xi@)yA=N(!g@6i?">i</field>
              </block>
            </value>
            <value name="value">
              <shadow type="logic_boolean" id="m=DdPX,GFx`u|)sdS09x">
                <field name="BOOL">FALSE</field>
              </shadow>
            </value>
          </block>
        </statement>
      </block>
    </statement>
  </block>
</xml>